CamAi/CamAiCamera.py
CamAi/CamAiCameraReader.py
CamAi/CamAiCameraWriter.py
CamAi/CamAiConfig.py
CamAi/CamAiDetection.py
CamAi/CamAiDetectionFaces.py
CamAi/CamAiDiscover.py
CamAi/CamAiManager.py
CamAi/CamAiMessage.py
CamAi/CamAiNotification.py
CamAi/CamAiPtz.py
CamAi/CamAiTraining.py
CamAi/CamAiUtils.py
CamAi/CamAiViewer.py
CamAi/__init__.py
CamAi/camaicli.py
CamAi/mrcnn_config.py
CamAi/mrcnn_model.py
CamAi/mrcnn_parallel_model.py
CamAi/mrcnn_utils.py
CamAi_castleguarders-0.0.1.data/scripts/camaicli.py
CamAi_castleguarders-0.0.1.dist-info/LICENSE
CamAi_castleguarders-0.0.1.dist-info/METADATA
CamAi_castleguarders-0.0.1.dist-info/WHEEL
CamAi_castleguarders-0.0.1.dist-info/top_level.txt
CamAi_castleguarders-0.0.1.dist-info/RECORD
