Metadata-Version: 2.1
Name: CamAi-castleguarders
Version: 0.0.1
Summary: AI based Camera monitor and alerting system
Home-page: https://github.com/castleguarders/CamAi
Author: Castle Guarders
Author-email: castleguarders@gmail.com
License: UNKNOWN
Platform: UNKNOWN
Classifier: Topic :: Multimedia :: Video
Classifier: Topic :: Multimedia :: Video :: Capture
Classifier: Topic :: Security
Classifier: Programming Language :: Python :: 3
Classifier: License :: OSI Approved :: MIT License
Classifier: Operating System :: OS Independent
Requires-Python: >=3.6
